pybythec/BuildElements.py
pybythec/BuildStatus.py
pybythec/__init__.py
pybythec/command_line.py
pybythec/utils.py
pybythec-0.9.22.dist-info/DESCRIPTION.rst
pybythec-0.9.22.dist-info/METADATA
pybythec-0.9.22.dist-info/RECORD
pybythec-0.9.22.dist-info/WHEEL
pybythec-0.9.22.dist-info/entry_points.txt
pybythec-0.9.22.dist-info/metadata.json
pybythec-0.9.22.dist-info/top_level.txt
