Metadata-Version: 2.0
Name: pybythec
Version: 0.9.22
Summary: A lightweight cross-platform build system for c/c++, written in python
Home-page: https://github.com/glowtree/pybythec
Author: glowtree
Author-email: tom@glowtree.com
License: LICENSE
Platform: UNKNOWN
